{
 "attach_print": 0,
 "channel": "Email",
 "condition": "",
 "creation": "2025-04-01 15:28:08.044021",
 "date_changed": "start_date",
 "days_in_advance": 1,
 "docstatus": 0,
 "doctype": "Notification",
 "document_type": "Property",
 "enabled": 1,
 "event": "Days Before",
 "idx": 0,
 "is_standard": 1,
 "message": "<!DOCTYPE html>\r\n<html lang=\"en\">\r\n<head>\r\n    <meta charset=\"UTF-8\">\r\n    <meta name=\"viewport\" content=\"width=device-width, initial-scale=1.0\">\r\n    \r\n    <style>\r\n        .container {\r\n            max-width: 600px;\r\n            margin: 0 auto;\r\n            padding: 20px;\r\n            border: 1px solid #ddd;\r\n            box-shadow: 0 0 10px rgba(0, 0, 0, 0.1);\r\n            font-family: Arial, sans-serif;\r\n        }\r\n        .header {\r\n            text-align: center;\r\n            padding-bottom: 20px;\r\n            border-bottom: 2px solid #4CAF50;\r\n            margin-bottom: 20px;\r\n        }\r\n        .congrats-banner {\r\n            background-color: #E8F5E9;\r\n            padding: 15px;\r\n            border-left: 5px solid #4CAF50;\r\n            margin: 20px 0;\r\n            font-size: 1.1em;\r\n        }\r\n        table {\r\n            width: 100%;\r\n            border-collapse: collapse;\r\n            margin: 15px 0;\r\n        }\r\n        table, th, td {\r\n            border: 1px solid #ddd;\r\n        }\r\n        th {\r\n            background-color: #4CAF50;\r\n            color: white;\r\n            padding: 10px;\r\n            text-align: left;\r\n        }\r\n        td {\r\n            padding: 8px;\r\n        }\r\n        .section-title {\r\n            color: #2E7D32;\r\n            font-size: 1.2em;\r\n            margin: 25px 0 10px 0;\r\n            border-bottom: 1px solid #E8F5E9;\r\n            padding-bottom: 5px;\r\n        }\r\n        .footer {\r\n            margin-top: 30px;\r\n            padding-top: 15px;\r\n            border-top: 1px solid #eee;\r\n            font-size: 0.9em;\r\n            color: #666;\r\n        }\r\n        .highlight {\r\n            font-weight: bold;\r\n            color: #2E7D32;\r\n        }\r\n    </style>\r\n</head>\r\n<body>\r\n    <div class=\"container\">\r\n        <div class=\"header\">\r\n            <h2 style=\"color: #2E7D32;\">Welcome to Your New Home!</h2>\r\n            <p>Congratulations on becoming our newest tenant at {{ property_name }}</p>\r\n        </div>\r\n\r\n        <div class=\"congrats-banner\">\r\n            We're delighted to welcome you to {{ property_name }}! This document confirms your successful application \r\n            and provides important details about your new home.\r\n        </div>\r\n\r\n        <div class=\"section-title\">Property Details</div>\r\n        <table>\r\n            <tr>\r\n                <th>Property Name</th>\r\n                <td>{{ property_name }}</td>\r\n            </tr>\r\n            <tr>\r\n                <th>Address</th>\r\n                <td>{{ address }}</td>\r\n            </tr>\r\n            <tr>\r\n                <th>Property Type</th>\r\n                <td>{{ property_type }}</td>\r\n            </tr>\r\n            <tr>\r\n                <th>Total Area</th>\r\n                <td>{{ total_area }} sq ft</td>\r\n            </tr>\r\n            <tr>\r\n                <th>Number of Floors</th>\r\n                <td>{{ number_of_floors }}</td>\r\n            </tr>\r\n        </table>\r\n\r\n        <div class=\"section-title\">Property Features</div>\r\n        <table>\r\n            <tr>\r\n                <th>Feature</th>\r\n                <th>Value</th>\r\n                <th>Specification</th>\r\n            </tr>\r\n            {% for feature in property_feature %}\r\n            <tr>\r\n                <td>{{ feature.feature }}</td>\r\n                <td>{{ feature.value }}</td>\r\n                <td>{{ feature.specification }}</td>\r\n            </tr>\r\n            {% endfor %}\r\n        </table>\r\n\r\n        <div class=\"section-title\">Payment Summary</div>\r\n        <table>\r\n            <tr>\r\n                <th>Charge Type</th>\r\n                <th>Mode</th>\r\n                <th>Payment Status</th>\r\n                <th>Amount</th>\r\n            </tr>\r\n            {% for charge in other_property_deal_charges %}\r\n            <tr>\r\n                <td>{{ charge.charge_type }}</td>\r\n                <td>{{ charge.mode }}</td>\r\n                <td>{{ charge.payment_status }}</td>\r\n                <td>{{ frappe.format_value(charge.amount, {\"fieldtype\": \"Currency\"}) }}</td>\r\n            </tr>\r\n            {% endfor %}\r\n        </table>\r\n\r\n        <div class=\"section-title\">Rental Agreement Summary</div>\r\n        <table>\r\n            <tr>\r\n                <th>Agreement Number</th>\r\n                <td>{{ rental_agreement_no }}</td>\r\n            </tr>\r\n            <tr>\r\n                <th>Start Date</th>\r\n                <td>{{ start_date }}</td>\r\n            </tr>\r\n            <tr>\r\n                <th>End Date</th>\r\n                <td>{{ end_date }}</td>\r\n            </tr>\r\n            <tr>\r\n                <th>Base Rent</th>\r\n                <td>{{ frappe.format_value(base_rent, {\"fieldtype\": \"Currency\"}) }}</td>\r\n            </tr>\r\n            <tr>\r\n                <th>Security Deposit</th>\r\n                <td>{{ frappe.format_value(security_deposit, {\"fieldtype\": \"Currency\"}) }}</td>\r\n            </tr>\r\n        </table>\r\n\r\n        <div class=\"section-title\">Next Steps</div>\r\n        <ul>\r\n            <li>Your keys will be available for pickup on <span class=\"highlight\">{{ start_date }}</span></li>\r\n            <li>Move-in inspection is scheduled for <span class=\"highlight\">{{ inspection_date or \"to be confirmed\" }}</span></li>\r\n            <li>Please review the attached rental agreement document</li>\r\n            <li>For any questions, contact your property manager {{ property_manager_name }} at {{ account_manager_mobile_phone }}</li>\r\n        </ul>\r\n\r\n        <div class=\"footer\">\r\n            <p>We're thrilled to have you as our tenant and hope you'll enjoy your new home!</p>\r\n            <p><b>{{ owner_name }}</b><br>Property Owner</p>\r\n            <p>Generated on: {{ frappe.utils.now_datetime().strftime('%Y-%m-%d') }}</p>\r\n        </div>\r\n    </div>\r\n</body>\r\n</html>",
 "message_type": "HTML",
 "modified": "2025-04-01 15:44:56.630607",
 "modified_by": "Administrator",
 "module": "Estate Management",
 "name": "Welcome to Your New Home!",
 "owner": "Administrator",
 "recipients": [
  {
   "receiver_by_document_field": "owner"
  }
 ],
 "send_system_notification": 0,
 "send_to_all_assignees": 0,
 "subject": "{{doc.client_name}} Welcome to Your New Home!"
}